materials_toolkit/__init__.py
materials_toolkit-0.1.2.dist-info/LICENSE
materials_toolkit-0.1.2.dist-info/METADATA
materials_toolkit-0.1.2.dist-info/WHEEL
materials_toolkit-0.1.2.dist-info/RECORD
